LICENSE
MANIFEST.in
README.md
setup.cfg
setup.py
crosstl/__init__.py
crosstl/_crosstl.py
crosstl/formatter.py
crosstl.egg-info/PKG-INFO
crosstl.egg-info/SOURCES.txt
crosstl.egg-info/dependency_links.txt
crosstl.egg-info/requires.txt
crosstl.egg-info/top_level.txt
crosstl/backend/CUDA/CudaAst.py
crosstl/backend/CUDA/CudaCrossGLCodeGen.py
crosstl/backend/CUDA/CudaLexer.py
crosstl/backend/CUDA/CudaParser.py
crosstl/backend/CUDA/__init__.py
crosstl/backend/DirectX/DirectxAst.py
crosstl/backend/DirectX/DirectxCrossGLCodeGen.py
crosstl/backend/DirectX/DirectxLexer.py
crosstl/backend/DirectX/DirectxParser.py
crosstl/backend/DirectX/__init__.py
crosstl/backend/GLSL/OpenglAst.py
crosstl/backend/GLSL/OpenglLexer.py
crosstl/backend/GLSL/OpenglParser.py
crosstl/backend/GLSL/__init__.py
crosstl/backend/GLSL/openglCrossglCodegen.py
crosstl/backend/HIP/HipAst.py
crosstl/backend/HIP/HipCrossGLCodeGen.py
crosstl/backend/HIP/HipLexer.py
crosstl/backend/HIP/HipParser.py
crosstl/backend/HIP/__init__.py
crosstl/backend/Metal/MetalAst.py
crosstl/backend/Metal/MetalCrossGLCodeGen.py
crosstl/backend/Metal/MetalLexer.py
crosstl/backend/Metal/MetalParser.py
crosstl/backend/Metal/__init__.py
crosstl/backend/Mojo/MojoAst.py
crosstl/backend/Mojo/MojoCrossGLCodeGen.py
crosstl/backend/Mojo/MojoLexer.py
crosstl/backend/Mojo/MojoParser.py
crosstl/backend/Mojo/__init__.py
crosstl/backend/Rust/RustAst.py
crosstl/backend/Rust/RustCrossGLCodeGen.py
crosstl/backend/Rust/RustLexer.py
crosstl/backend/Rust/RustParser.py
crosstl/backend/Rust/__init__.py
crosstl/backend/SPIRV/VulkanAst.py
crosstl/backend/SPIRV/VulkanCrossGLCodeGen.py
crosstl/backend/SPIRV/VulkanLexer.py
crosstl/backend/SPIRV/VulkanParser.py
crosstl/backend/SPIRV/__init__.py
crosstl/translator/__init__.py
crosstl/translator/ast.py
crosstl/translator/lexer.py
crosstl/translator/parser.py
crosstl/translator/codegen/GLSL_codegen.py
crosstl/translator/codegen/SPIRV_codegen.py
crosstl/translator/codegen/__init__.py
crosstl/translator/codegen/array_utils.py
crosstl/translator/codegen/ast_utils.py
crosstl/translator/codegen/cuda_codegen.py
crosstl/translator/codegen/directx_codegen.py
