Metadata-Version: 2.1
Name: crosstl
Version: 1.0.0
Summary: CrossTL: Universal Programming Language and Translator
Home-page: https://crossgl.net/
Author: CrossGL team
Author-email: nripesh@crossgl.net
Project-URL: Documentation, https://crossgl.github.io/crossgl-docs/
Classifier: Programming Language :: Python :: 3
Classifier: Operating System :: OS Independent
Requires-Python: >=3.8
License-File: LICENSE
